{"nodes": [{"id": "n1", "predicate": "bring_about", "args": ["DTC"]}, {"id": "n4", "predicate": "bring_about", "args": ["AJU"]}, {"id": "n5", "predicate": "means_to", "args": ["DTC", "AJU"]}, {"id": "n6", "predicate": "acceptable", "args": ["DRI"]}], "edges": [{"id": "e3", "from": "n1", "to": "n4"}, {"id": "e4", "from": "n5", "to": "n4"}, {"id": "e5", "from": "n6", "to": "n5"}], "variables": {"DTC": {"type": "Action", "text": "DNA testing in criminal cases"}, "DRI": {"type": "Proposition", "text": "DNA is a reliable identifier."}, "AJU": {"type": "Case", "text": "accurate judgment"}}, "instances": [{"id": "i2", "idiom_id": "I04", "node_map": {"C": "n1", "P1": "n4", "P2": "n5"}}], "default_inferences": ["e5"]}